pandoc4ssg/__init__.py
pandoc4ssg/dirStruct.py
pandoc4ssg/pipeline.py
pandoc4ssg/postHandler.py
pandoc4ssg/utils.py
pandoc4ssg-0.0.1.dist-info/METADATA
pandoc4ssg-0.0.1.dist-info/WHEEL
pandoc4ssg-0.0.1.dist-info/top_level.txt
pandoc4ssg-0.0.1.dist-info/RECORD
