Metadata-Version: 2.1
Name: pandoc4ssg
Version: 0.0.1
Summary: Using Pandoc with Static Site Generators
Home-page: http://github.com/liao961120/pandoc4ssg
Author: Yongfu Liao
Author-email: liao961120@github.com
License: MIT
Platform: UNKNOWN
Requires-Dist: pypandoc
Requires-Dist: pyyaml
Requires-Dist: toml
